timezones/__init__.py
timezones/_defs.py
timezones/py.typed
timezones/test_timezones.py
timezones/tz_rendering.py
timezones/tz_utils.py
timezones/zones.py
timezones-3.0.0.dist-info/LICENSE
timezones-3.0.0.dist-info/METADATA
timezones-3.0.0.dist-info/WHEEL
timezones-3.0.0.dist-info/RECORD
