Metadata-Version: 2.1
Name: timezones
Version: 3.0.0
Summary: A Python library that provides better selection of common timezones, can output HTML and auto select the best timezone based on user's IP.
Home-page: https://doist.com
License: MIT
Keywords: timezones,timezone
Author: Doist Developers
Author-email: dev@doist.com
Requires-Python: >=3.11,<4.0
Classifier: Development Status :: 5 - Production/Stable
Classifier: Intended Audience :: Developers
Classifier: License :: OSI Approved :: MIT License
Classifier: Operating System :: OS Independent
Classifier: Programming Language :: Python
Classifier: Programming Language :: Python :: 3
Classifier: Programming Language :: Python :: 3.11
Classifier: Programming Language :: Python :: 3.12
Classifier: Programming Language :: Python :: 3.13
Classifier: Topic :: Software Development :: Libraries :: Python Modules
